image2world/__init__.py
image2world/image2worldlib.py
image2world/interface.py
image2world/validate.py
image2worldlib/__init__.py
image2worldlib/image2worldlib.py
image2worldlib/interface.py
image2worldlib/validate.py
image2world-0.2.7.dist-info/LICENSE
image2world-0.2.7.dist-info/METADATA
image2world-0.2.7.dist-info/WHEEL
image2world-0.2.7.dist-info/top_level.txt
image2world-0.2.7.dist-info/RECORD
